flask_selfdoc/__init__.py
flask_selfdoc/autodoc.py
flask_selfdoc/templates/autodoc_default.html
flask_selfdoc-1.3.0.dist-info/entry_points.txt
flask_selfdoc-1.3.0.dist-info/LICENSE
flask_selfdoc-1.3.0.dist-info/WHEEL
flask_selfdoc-1.3.0.dist-info/METADATA
flask_selfdoc-1.3.0.dist-info/RECORD
